imaspy/__init__.py
imaspy/ids_classes.py
imaspy/imas_ual_env_parsing.py
imaspy/setup_logging.py
imaspy/test_init.py
imaspy/test_minimal.py
imaspy/test_minimal_types.py
imaspy/version.py
imaspy/backends/__init__.py
imaspy/backends/common.py
imaspy/backends/file_manager.py
imaspy/backends/ual.py
imaspy/backends/xarray_core_indexing.py
imaspy/backends/xarray_core_utils.py
imaspy/examples/ids_dummy_class.py
imaspy/examples/read_write_nbi.py
imaspy-0.1.1.dist-info/COPYING
imaspy-0.1.1.dist-info/COPYING.LESSER
imaspy-0.1.1.dist-info/LICENSE
imaspy-0.1.1.dist-info/METADATA
imaspy-0.1.1.dist-info/WHEEL
imaspy-0.1.1.dist-info/top_level.txt
imaspy-0.1.1.dist-info/RECORD
