Metadata-Version: 2.1
Name: imaspy
Version: 0.1.1
Summary: Pythonic wrappers for the IMAS Access Layer
Home-page: https://gitlab.com/klimex/imaspy
Author: Karel van de Plassche
Author-email: k.l.vandeplassche@differ.nl
License: UNKNOWN
Platform: UNKNOWN
Classifier: Intended Audience :: Science/Research
Classifier: License :: OSI Approved :: GNU Lesser General Public License v3 or later (LGPLv3+)
Classifier: Natural Language :: English
Classifier: Programming Language :: Python :: 3
Classifier: Topic :: Utilities
Requires-Python: >3.6
Requires-Dist: numpy (>=1.15.4)
Requires-Dist: IPython (>=7.2.0)
Provides-Extra: all
Requires-Dist: imas ; extra == 'all'
Requires-Dist: pytest (>=5.4.1) ; extra == 'all'
Requires-Dist: pytest-cov (>=0.6) ; extra == 'all'
Requires-Dist: sphinx (>=3.2.1) ; extra == 'all'
Requires-Dist: sphinx-rtd-theme (>=0.5) ; extra == 'all'
Requires-Dist: recommonmark (>=0.6) ; extra == 'all'
Requires-Dist: sphinx-autosummary-accessors (>=0.1.2) ; extra == 'all'
Provides-Extra: backends_al
Requires-Dist: imas ; extra == 'backends_al'
Provides-Extra: backends_xarray
Provides-Extra: docs
Requires-Dist: sphinx (>=3.2.1) ; extra == 'docs'
Requires-Dist: sphinx-rtd-theme (>=0.5) ; extra == 'docs'
Requires-Dist: recommonmark (>=0.6) ; extra == 'docs'
Requires-Dist: sphinx-autosummary-accessors (>=0.1.2) ; extra == 'docs'
Provides-Extra: examples
Requires-Dist: imas ; extra == 'examples'
Provides-Extra: test
Requires-Dist: pytest (>=5.4.1) ; extra == 'test'
Requires-Dist: pytest-cov (>=0.6) ; extra == 'test'
